aidial_integration_langchain/__init__.py
aidial_integration_langchain/patch/__init__.py
aidial_integration_langchain/patch/decorators.py
aidial_integration_langchain-0.1.0.dist-info/WHEEL
aidial_integration_langchain-0.1.0.dist-info/METADATA
aidial_integration_langchain-0.1.0.dist-info/RECORD
