Metadata-Version: 2.4
Name: aidial-integration-langchain
Version: 0.1.0
Summary: Utilities for integration of AI DIAL API with Langchain library
Author: EPAM RAIL
Author-email: EPAM RAIL <SpecialEPM-DIALDevTeam@epam.com>
License-Expression: Apache-2.0
Requires-Dist: langchain<0.4
Requires-Dist: langchain-core<0.4
Requires-Dist: langchain-openai>=0.1.1,<0.4
Requires-Dist: openai>=1.48,<2
Requires-Dist: flake8>=6.0.0 ; extra == 'lint'
Requires-Dist: black>=23.3,<25.0 ; extra == 'lint'
Requires-Dist: isort>=5.12.0 ; extra == 'lint'
Requires-Dist: pyright>=1.1.324 ; extra == 'lint'
Requires-Dist: autoflake>=2.2.0 ; extra == 'lint'
Requires-Dist: pytest>=7.4.2 ; extra == 'test'
Requires-Dist: pytest-asyncio>=0.21.1 ; extra == 'test'
Requires-Dist: httpx==0.27.2 ; extra == 'test'
Requires-Python: >=3.9, <4.0
Provides-Extra: lint
Provides-Extra: test
